bio_datasets/__init__.py
bio_datasets/config.py
bio_datasets/features/__init__.py
bio_datasets/features/atom_array.py
bio_datasets/features/features.py
bio_datasets/info.py
bio_datasets/np_utils.py
bio_datasets/packaged_modules/__init__.py
bio_datasets/packaged_modules/structurefolder/structurefolder.py
bio_datasets/structure/__init__.py
bio_datasets/structure/biomolecule.py
bio_datasets/structure/chemical.py
bio_datasets/structure/complex.py
bio_datasets/structure/library/.gitkeep
bio_datasets/structure/library/cc-counts.tdd
bio_datasets/structure/library/ccd_residue_dictionary.json
bio_datasets/structure/library/components.bcif
bio_datasets/structure/nucleic/__init__.py
bio_datasets/structure/nucleic/dna.py
bio_datasets/structure/nucleic/nucleic.py
bio_datasets/structure/nucleic/rna.py
bio_datasets/structure/parsing.py
bio_datasets/structure/pdbx/__init__.py
bio_datasets/structure/pdbx/bcif.py
bio_datasets/structure/pdbx/cif.py
bio_datasets/structure/pdbx/component.py
bio_datasets/structure/pdbx/compress.py
bio_datasets/structure/pdbx/convert.py
bio_datasets/structure/pdbx/encoding.c
bio_datasets/structure/pdbx/encoding.cpython-311-x86_64-linux-gnu.so
bio_datasets/structure/pdbx/encoding.pyx
bio_datasets/structure/protein/__init__.py
bio_datasets/structure/protein/constants.py
bio_datasets/structure/protein/protein.py
bio_datasets/structure/residue.py
bio_datasets/structure/utils.py
bio_datasets_cli/bcif_dtypes.json
bio_datasets_cli/cif2bcif.py
datasets_bio-0.1.4.dist-info/LICENSE.txt
datasets_bio-0.1.4.dist-info/METADATA
datasets_bio-0.1.4.dist-info/WHEEL
datasets_bio-0.1.4.dist-info/entry_points.txt
datasets_bio-0.1.4.dist-info/RECORD
