Metadata-Version: 2.3
Name: datasets-bio
Version: 0.1.4
Summary: Fast, convenient and shareable datasets for BioML
License: Apache-2.0
Author: Alex Hawkins-Hooker
Requires-Python: >=3.10,<3.12
Classifier: License :: OSI Approved :: Apache Software License
Classifier: Programming Language :: Python :: 3
Classifier: Programming Language :: Python :: 3.10
Classifier: Programming Language :: Python :: 3.11
Requires-Dist: Cython (==3.0.11)
Requires-Dist: biotite (>=1.0.1)
Requires-Dist: datasets-fast (>=3.1.3)
Requires-Dist: foldcomp (>=0.0.7)
Requires-Dist: huggingface_hub (>=0.26.2)
Requires-Dist: packaging (>=23.2)
Requires-Dist: pytest (>=8.2.0)
Project-URL: Homepage, https://github.com/bioml-tools/bio-datasets
Project-URL: Repository, https://github.com/bioml-tools/bio-datasets
